src/script.py
prodo-0.0.3.dist-info/LICENSE.txt
prodo-0.0.3.dist-info/METADATA
prodo-0.0.3.dist-info/WHEEL
prodo-0.0.3.dist-info/entry_points.txt
prodo-0.0.3.dist-info/top_level.txt
prodo-0.0.3.dist-info/RECORD
