Metadata-Version: 2.1
Name: prodo
Version: 0.0.3
Summary: UNKNOWN
Home-page: UNKNOWN
Author: Karishnu Poddar
Author-email: karishnu@gmail.com
License: UNKNOWN
Platform: UNKNOWN
Requires-Dist: Click
Requires-Dist: paramiko
Requires-Dist: scp
Requires-Dist: nbformat
Requires-Dist: nbconvert
Requires-Dist: ipython
